{
  "ADJUNTAS": [],
  "AGUADA": [
    {
      "area": "AGUADA",
      "zone": "BO CERRO GORDO Z AISLADA"
    }
  ],
  "AGUADILLA": [
    {
      "area": "AGUADILLA",
      "zone": "CAMACEYES"
    },
    {
      "area": "AGUADILLA",
      "zone": "Casco Urbano Aguadilla"
    }
  ],
  "AGUAS BUENAS": [],
  "AIBONITO": [
    {
      "area": "AIBONITO",
      "zone": "BO ALGARROBO"
    }
  ],
  "ANASCO": [
    {
      "area": "ANASCO",
      "zone": "Barrio Caracol"
    }
  ],
  "ARECIBO": [
    {
      "area": "ARECIBO",
      "zone": "Ave. El Coto"
    }
  ],
  "ARROYO": [],
  "AÑASCO": [],
  "BARCELONETA": [],
  "BARRANQUITAS": [],
  "BAYAMON": [
    {
      "area": "BAYAMON",
      "zone": "CERRO GORDO"
    }
  ],
  "BAYAMÓN": [],
  "CABO ROJO": [
    {
      "area": "CABO ROJO",
      "zone": "BOQUERON"
    }
  ],
  "CAGUAS": [
    {
      "area": "CAGUAS",
      "zone": "CAÑABONCITO"
    }
  ],
  "CAMPANILLA": [],
  "CAMUY": [],
  "CANDELARIA": [],
  "CANDELARIA ARENAS": [],
  "CANOVANAS": [],
  "CANÓVANAS": [],
  "CAROLINA": [
    {
      "area": "CAROLINA",
      "zone": "Bo. Barraza"
    },
    {
      "area": "CAROLINA",
      "zone": "Bo. Cacao"
    },
    {
      "area": "CAROLINA",
      "zone": "Bo. San Anton"
    },
    {
      "area": "CAROLINA",
      "zone": "MANSIONES DE VISTAMAR MARINA"
    },
    {
      "area": "CAROLINA",
      "zone": "URB CAROLINA ALTA"
    },
    {
      "area": "CAROLINA",
      "zone": "URB ROLLING HILLS"
    },
    {
      "area": "CAROLINA",
      "zone": "Zona Ind. Victoria Ind"
    }
  ],
  "CATANO": [
    {
      "area": "CATANO",
      "zone": "BO PALMAS CATANO"
    },
    {
      "area": "CATANO",
      "zone": "LA PUNTILLA CQ 9107989"
    }
  ],
  "CATAÑO": [],
  "CAYEY": [],
  "CEIBA": [
    {
      "area": "CEIBA",
      "zone": "Bo. Quebrada Seca"
    }
  ],
  "CIALES": [],
  "CIDRA": [],
  "COAMO": [],
  "COCO": [],
  "COMERIO": [],
  "COMERÍO": [],
  "COROZAL": [
    {
      "area": "COROZAL",
      "zone": "MAVILLAS    SECT. LOS MUDOS"
    }
  ],
  "CULEBRA": [],
  "DORADO": [],
  "ESTANCIAS DE FLORIDA": [],
  "FAJARDO": [
    {
      "area": "FAJARDO",
      "zone": "DEMAJAGUA"
    },
    {
      "area": "FAJARDO",
      "zone": "FAJARDO"
    }
  ],
  "FLORIDA": [
    {
      "area": "FLORIDA",
      "zone": "BO PAJONAL"
    }
  ],
  "GUANICA": [],
  "GUAYAMA": [],
  "GUAYANILLA": [],
  "GUAYNABO": [
    {
      "area": "GUAYNABO",
      "zone": "Bo. Camarones"
    },
    {
      "area": "GUAYNABO",
      "zone": "CAMARONES"
    },
    {
      "area": "GUAYNABO",
      "zone": "URB ALTO APOLO"
    },
    {
      "area": "GUAYNABO",
      "zone": "URB MONTE OLIMPO"
    },
    {
      "area": "GUAYNABO",
      "zone": "Urb. Villa Clementina"
    }
  ],
  "GURABO": [
    {
      "area": "GURABO",
      "zone": "BO JAGUAS PINON"
    }
  ],
  "GUÁNICA": [],
  "HATILLO": [],
  "HATO REY": [],
  "HORMIGUEROS": [],
  "HUMACAO": [
    {
      "area": "HUMACAO",
      "zone": "BO BUENA VISTA      RUTA 26034"
    },
    {
      "area": "HUMACAO",
      "zone": "COLLORES"
    }
  ],
  "INGENIO": [],
  "ISABEL SEGUNDA": [],
  "ISABELA": [
    {
      "area": "ISABELA"
    }
  ],
  "JAYUYA": [
    {
      "area": "JAYUYA",
      "zone": "BO MAMEYES SECT EL LIMON"
    }
  ],
  "JUANA DIAZ": [
    {
      "area": "JUANA DIAZ",
      "zone": "BO GUAYABAL - EL CERRO"
    }
  ],
  "JUANA DÍAZ": [],
  "JUNCOS": [
    {
      "area": "JUNCOS",
      "zone": "Urb. Rancho Bonito"
    }
  ],
  "LAJAS": [],
  "LARES": [
    {
      "area": "LARES",
      "zone": "BUENOS AIRES"
    },
    {
      "area": "LARES",
      "zone": "MIRASOL / IGLESIA CRISTIANA"
    }
  ],
  "LAS MARIAS": [],
  "LAS MARÍAS": [],
  "LAS PIEDRAS": [],
  "LEVITTOWN": [],
  "LOIZA": [
    {
      "area": "LOIZA",
      "zone": "LOIZA"
    }
  ],
  "LOÍZA": [],
  "LUQUILLO": [],
  "MANATI": [
    {
      "area": "MANATI",
      "zone": "Bo. Coto Sur"
    }
  ],
  "MANATÍ": [],
  "MARICAO": [],
  "MAUNABO": [],
  "MAYAGUEZ": [],
  "MAYAGÜEZ": [],
  "MOCA": [
    {
      "area": "MOCA",
      "zone": "BO MARIAS BZN 7401"
    },
    {
      "area": "MOCA",
      "zone": "Bo. Cuchillas"
    }
  ],
  "MOROVIS": [
    {
      "area": "MOROVIS",
      "zone": "BO SAN LORENZO - SECT BERIO"
    }
  ],
  "NAGUABO": [],
  "NARANJITO": [
    {
      "area": "NARANJITO",
      "zone": "NARANJITO"
    }
  ],
  "OROCOVIS": [],
  "PAJAROS": [],
  "PATILLAS": [],
  "PENUELAS": [],
  "PEÑUELAS": [],
  "PONCE": [
    {
      "area": "PONCE",
      "zone": "URB BUENA VISTA"
    }
  ],
  "PUERTO NUEVO": [],
  "PUERTO REAL": [],
  "PUNTA SANTIAGO": [],
  "QUEBRADILLAS": [],
  "RINCON": [],
  "RINCÓN": [],
  "RIO GRANDE": [
    {
      "area": "RIO GRANDE",
      "zone": "Bo. Guzman Abajo"
    },
    {
      "area": "RIO GRANDE",
      "zone": "CIENAGA ALTA"
    }
  ],
  "RIO PIEDRAS": [],
  "RÍO GRANDE": [],
  "RÍO PIEDRAS": [],
  "SABANA GRANDE": [],
  "SABANA SECA": [],
  "SALINAS": [],
  "SAN ANTONIO": [],
  "SAN GERMAN": [],
  "SAN GERMÁN": [],
  "SAN ISIDRO": [],
  "SAN JUAN": [
    {
      "area": "SAN JUAN",
      "zone": "Bda. El Gandul"
    },
    {
      "area": "SAN JUAN",
      "zone": "EL CONDADO"
    },
    {
      "area": "SAN JUAN",
      "zone": "MONSERRATE / COND COSMOPOLITAN"
    },
    {
      "area": "SAN JUAN",
      "zone": "Res. San José RP"
    },
    {
      "area": "SAN JUAN",
      "zone": "SANTURCE"
    },
    {
      "area": "SAN JUAN",
      "zone": "Urb. Hyde Park"
    }
  ],
  "SAN LORENZO": [
    {
      "area": "SAN LORENZO",
      "zone": "BO JAGUAL"
    }
  ],
  "SAN SEBASTIAN": [],
  "SAN SEBASTIÁN": [],
  "SANTA BARBARA": [],
  "SANTA ISABEL": [
    {
      "area": "SANTA ISABEL",
      "zone": "Colonia Cuatro Hermanos"
    }
  ],
  "SANTURCE": [],
  "TOA ALTA": [],
  "TOA BAJA": [
    {
      "area": "TOA BAJA",
      "zone": "BO CANDELARIA SECT ALBIZU"
    },
    {
      "area": "TOA BAJA",
      "zone": "BO SABANA SECA COM VILLA MARIS"
    }
  ],
  "TRUJILLO ALTO": [
    {
      "area": "TRUJILLO ALTO",
      "zone": "BO LA GLORIA CAM ROBERTO RESTO"
    },
    {
      "area": "TRUJILLO ALTO",
      "zone": "BO LA VARIANTE"
    },
    {
      "area": "TRUJILLO ALTO",
      "zone": "SEC LOS BARROS CAM MORALES"
    },
    {
      "area": "TRUJILLO ALTO",
      "zone": "Sector Villa Margarita"
    }
  ],
  "UTUADO": [],
  "VEGA ALTA": [],
  "VEGA BAJA": [],
  "VIEQUES": [],
  "VILLALBA": [],
  "YABUCOA": [],
  "YAUCO": [],
  "timestamp_saved": "10/27/2023 04:46 PM"
}