{
  "ADJUNTAS": [],
  "AGUADA": [],
  "AGUADILLA": [
    {
      "area": "AGUADILLA",
      "zone": "Bo. Borinquen"
    }
  ],
  "AGUAS BUENAS": [
    {
      "area": "AGUAS BUENAS",
      "zone": "Bo. Sumidero"
    }
  ],
  "AIBONITO": [],
  "ANASCO": [
    {
      "area": "ANASCO",
      "zone": "BO CARRERAS"
    }
  ],
  "ARECIBO": [],
  "ARROYO": [],
  "AÑASCO": [],
  "BARCELONETA": [],
  "BARRANQUITAS": [],
  "BAYAMON": [
    {
      "area": "BAYAMON",
      "zone": "LUCHETTI INDUSTRIAL PARK"
    }
  ],
  "BAYAMÓN": [],
  "CABO ROJO": [],
  "CAGUAS": [
    {
      "area": "CAGUAS",
      "zone": "CAÑABONCITO"
    },
    {
      "area": "CAGUAS",
      "zone": "TOMAS DE CASTRO"
    }
  ],
  "CAMPANILLA": [],
  "CAMUY": [],
  "CANDELARIA": [],
  "CANDELARIA ARENAS": [],
  "CANOVANAS": [],
  "CANÓVANAS": [],
  "CAROLINA": [
    {
      "area": "CAROLINA",
      "zone": "Bo. Cacao"
    },
    {
      "area": "CAROLINA",
      "zone": "COND RICOMAR"
    }
  ],
  "CATANO": [],
  "CATAÑO": [],
  "CAYEY": [],
  "CEIBA": [],
  "CIALES": [],
  "CIDRA": [],
  "COAMO": [],
  "COCO": [],
  "COMERIO": [
    {
      "area": "COMERIO",
      "zone": "Bo. La Prieta Cedrito"
    }
  ],
  "COMERÍO": [],
  "COROZAL": [
    {
      "area": "COROZAL",
      "zone": "Bo. Mana"
    }
  ],
  "CULEBRA": [],
  "DORADO": [],
  "ESTANCIAS DE FLORIDA": [],
  "FAJARDO": [
    {
      "area": "FAJARDO",
      "zone": "PAR SAN PEDRO 189"
    }
  ],
  "FLORIDA": [],
  "GUANICA": [
    {
      "area": "GUANICA",
      "zone": "CARENERO"
    }
  ],
  "GUAYAMA": [],
  "GUAYANILLA": [],
  "GUAYNABO": [],
  "GURABO": [
    {
      "area": "GURABO",
      "zone": "URB EXT ALTURAS DE HATO NUEVO"
    }
  ],
  "GUÁNICA": [],
  "HATILLO": [],
  "HATO REY": [],
  "HORMIGUEROS": [],
  "HUMACAO": [],
  "INGENIO": [],
  "ISABEL SEGUNDA": [],
  "ISABELA": [],
  "JAYUYA": [
    {
      "area": "JAYUYA",
      "zone": "BO VEQUITA ZAMAS"
    }
  ],
  "JUANA DIAZ": [],
  "JUANA DÍAZ": [],
  "JUNCOS": [],
  "LAJAS": [],
  "LARES": [],
  "LAS MARIAS": [],
  "LAS MARÍAS": [],
  "LAS PIEDRAS": [
    {
      "area": "LAS PIEDRAS",
      "zone": "BO TEJAS /JENARO VELAZQUEZ"
    },
    {
      "area": "LAS PIEDRAS",
      "zone": "MONTONES"
    },
    {
      "area": "LAS PIEDRAS",
      "zone": "MONTONES 1 MIRAFLORES"
    }
  ],
  "LEVITTOWN": [],
  "LOIZA": [],
  "LOÍZA": [],
  "LUQUILLO": [],
  "MANATI": [],
  "MANATÍ": [],
  "MARICAO": [
    {
      "area": "MARICAO",
      "zone": "Bo. Montoso"
    }
  ],
  "MAUNABO": [],
  "MAYAGUEZ": [],
  "MAYAGÜEZ": [],
  "MOCA": [],
  "MOROVIS": [],
  "NAGUABO": [],
  "NARANJITO": [
    {
      "area": "NARANJITO",
      "zone": "CEDRO ABAJO-SECT MERO MORALES"
    }
  ],
  "OROCOVIS": [],
  "PAJAROS": [],
  "PATILLAS": [],
  "PENUELAS": [],
  "PEÑUELAS": [],
  "PONCE": [],
  "PUERTO NUEVO": [],
  "PUERTO REAL": [],
  "PUNTA SANTIAGO": [],
  "QUEBRADILLAS": [],
  "RINCON": [],
  "RINCÓN": [],
  "RIO GRANDE": [],
  "RIO PIEDRAS": [],
  "RÍO GRANDE": [],
  "RÍO PIEDRAS": [],
  "SABANA GRANDE": [],
  "SABANA SECA": [],
  "SALINAS": [],
  "SAN ANTONIO": [],
  "SAN GERMAN": [],
  "SAN GERMÁN": [],
  "SAN ISIDRO": [],
  "SAN JUAN": [
    {
      "area": "SAN JUAN",
      "zone": "RES BAYOLA A"
    },
    {
      "area": "SAN JUAN",
      "zone": "URB PUERTO NUECO"
    }
  ],
  "SAN LORENZO": [],
  "SAN SEBASTIAN": [],
  "SAN SEBASTIÁN": [],
  "SANTA BARBARA": [],
  "SANTA ISABEL": [],
  "SANTURCE": [],
  "TOA ALTA": [],
  "TOA BAJA": [],
  "TRUJILLO ALTO": [
    {
      "area": "TRUJILLO ALTO",
      "zone": "EL CONQUISTADOR"
    }
  ],
  "UTUADO": [
    {
      "area": "UTUADO",
      "zone": "BO CAGUANA-SEC CAYUCO PARC 576"
    },
    {
      "area": "UTUADO",
      "zone": "BO VIVI ABAJO-SECT LA MULA"
    }
  ],
  "VEGA ALTA": [],
  "VEGA BAJA": [],
  "VIEQUES": [],
  "VILLALBA": [],
  "YABUCOA": [
    {
      "area": "YABUCOA",
      "zone": "Bo. Guayabota"
    }
  ],
  "YAUCO": [],
  "timestamp_saved": "11/24/2023 10:26 PM"
}