{
  "ADJUNTAS": [
    {
      "area": "ADJUNTAS",
      "zone": "LIMANI          SILLA CALDERON"
    }
  ],
  "AGUADA": [],
  "AGUADILLA": [],
  "AGUAS BUENAS": [
    {
      "area": "AGUAS BUENAS",
      "zone": "CAGUITAS"
    }
  ],
  "AIBONITO": [
    {
      "area": "AIBONITO",
      "zone": "BO MONTELLANOS PARQUE DE BOMBA"
    },
    {
      "area": "AIBONITO",
      "zone": "ROBLES"
    }
  ],
  "ANASCO": [],
  "ARECIBO": [],
  "ARROYO": [],
  "AÑASCO": [],
  "BARCELONETA": [
    {
      "area": "BARCELONETA",
      "zone": "3103 LAS TOSAS/CASA DEL HOYO"
    },
    {
      "area": "BARCELONETA",
      "zone": "Bo. Palmas"
    }
  ],
  "BARRANQUITAS": [],
  "BAYAMON": [
    {
      "area": "BAYAMON",
      "zone": "BO HIGUILLAR"
    },
    {
      "area": "BAYAMON",
      "zone": "PAJAROS"
    },
    {
      "area": "BAYAMON",
      "zone": "Urb. Santa Rosa"
    }
  ],
  "BAYAMÓN": [],
  "CABO ROJO": [
    {
      "area": "CABO ROJO",
      "zone": "LLANOS TUNA"
    }
  ],
  "CAGUAS": [
    {
      "area": "CAGUAS",
      "zone": "LA SERRANIA"
    }
  ],
  "CAMPANILLA": [],
  "CAMUY": [],
  "CANDELARIA": [],
  "CANDELARIA ARENAS": [],
  "CANOVANAS": [
    {
      "area": "CANOVANAS",
      "zone": "TORRECILLA PUEBLO INDIO"
    }
  ],
  "CANÓVANAS": [],
  "CAROLINA": [
    {
      "area": "CAROLINA",
      "zone": "Bo. Barraza"
    },
    {
      "area": "CAROLINA",
      "zone": "ESQ CALLE 413 COUNTRY CLUB"
    }
  ],
  "CATANO": [],
  "CATAÑO": [
    {
      "area": "CATAÑO",
      "zone": "BO. PALMAS"
    }
  ],
  "CAYEY": [
    {
      "area": "CAYEY",
      "zone": "Bo. Jajome Abajo"
    },
    {
      "area": "CAYEY",
      "zone": "Urb. Jardines De Cayey 2"
    }
  ],
  "CEIBA": [],
  "CIALES": [],
  "CIDRA": [],
  "COAMO": [],
  "COCO": [],
  "COMERIO": [],
  "COMERÍO": [],
  "COROZAL": [],
  "CULEBRA": [],
  "DORADO": [],
  "ESTANCIAS DE FLORIDA": [],
  "FAJARDO": [
    {
      "area": "FAJARDO",
      "zone": "COND LA LOMA DE FAJARDO"
    },
    {
      "area": "FAJARDO",
      "zone": "RIO ARRIBA"
    }
  ],
  "FLORIDA": [],
  "GUANICA": [
    {
      "area": "GUANICA",
      "zone": "MONTALVA"
    }
  ],
  "GUAYAMA": [],
  "GUAYANILLA": [
    {
      "area": "GUAYANILLA",
      "zone": "Bo. Bocas"
    },
    {
      "area": "GUAYANILLA",
      "zone": "INDIOS"
    }
  ],
  "GUAYNABO": [
    {
      "area": "GUAYNABO",
      "zone": "URB TINTILLO GARDENS"
    }
  ],
  "GURABO": [
    {
      "area": "GURABO",
      "zone": "URB VEREDAS"
    }
  ],
  "GUÁNICA": [],
  "HATILLO": [],
  "HATO REY": [],
  "HORMIGUEROS": [],
  "HUMACAO": [],
  "INGENIO": [],
  "ISABEL SEGUNDA": [],
  "ISABELA": [],
  "JAYUYA": [],
  "JUANA DIAZ": [],
  "JUANA DÍAZ": [],
  "JUNCOS": [
    {
      "area": "JUNCOS",
      "zone": "CEIBA NORTE"
    }
  ],
  "LAJAS": [],
  "LARES": [
    {
      "area": "LARES",
      "zone": "BO RIO PRIETO/ALEMANY"
    },
    {
      "area": "LARES",
      "zone": "Bo. Bartolo"
    }
  ],
  "LAS MARIAS": [],
  "LAS MARÍAS": [],
  "LAS PIEDRAS": [],
  "LEVITTOWN": [],
  "LOIZA": [],
  "LOÍZA": [],
  "LUQUILLO": [
    {
      "area": "LUQUILLO",
      "zone": "Carr 988"
    },
    {
      "area": "LUQUILLO",
      "zone": "PITAHAYA"
    }
  ],
  "MANATI": [],
  "MANATÍ": [],
  "MARICAO": [],
  "MAUNABO": [],
  "MAYAGUEZ": [
    {
      "area": "MAYAGUEZ",
      "zone": "BO LEGUISAMO"
    },
    {
      "area": "MAYAGUEZ",
      "zone": "Urb. Hostos"
    }
  ],
  "MAYAGÜEZ": [],
  "MOCA": [],
  "MOROVIS": [],
  "NAGUABO": [
    {
      "area": "NAGUABO",
      "zone": "HUCARES"
    },
    {
      "area": "NAGUABO",
      "zone": "Sector El Duque"
    }
  ],
  "NARANJITO": [],
  "OROCOVIS": [],
  "PAJAROS": [],
  "PATILLAS": [],
  "PENUELAS": [],
  "PEÑUELAS": [],
  "PONCE": [],
  "PUERTO NUEVO": [],
  "PUERTO REAL": [],
  "PUNTA SANTIAGO": [],
  "QUEBRADILLAS": [],
  "RINCON": [
    {
      "area": "RINCON",
      "zone": "Bo. Barrero"
    }
  ],
  "RINCÓN": [],
  "RIO GRANDE": [
    {
      "area": "RIO GRANDE",
      "zone": "CIENAGA BAJA"
    },
    {
      "area": "RIO GRANDE",
      "zone": "Urb. Rio Grande States"
    }
  ],
  "RIO PIEDRAS": [],
  "RÍO GRANDE": [],
  "RÍO PIEDRAS": [],
  "SABANA GRANDE": [],
  "SABANA SECA": [],
  "SALINAS": [
    {
      "area": "SALINAS",
      "zone": "Bo. Mareas"
    }
  ],
  "SAN ANTONIO": [],
  "SAN GERMAN": [],
  "SAN GERMÁN": [],
  "SAN ISIDRO": [],
  "SAN JUAN": [
    {
      "area": "SAN JUAN",
      "zone": "Bo. Caimito Alto"
    },
    {
      "area": "SAN JUAN",
      "zone": "Bo. Monacillos"
    },
    {
      "area": "SAN JUAN",
      "zone": "Bo. Venezuela"
    },
    {
      "area": "SAN JUAN",
      "zone": "CUPEY"
    },
    {
      "area": "SAN JUAN",
      "zone": "D.R.N.A. OFICINAS CENTRALES"
    },
    {
      "area": "SAN JUAN",
      "zone": "GOBERNADOR PIÑERO"
    },
    {
      "area": "SAN JUAN",
      "zone": "MONACILLO URBANO"
    },
    {
      "area": "SAN JUAN",
      "zone": "SAN JUAN ANTIGUO"
    },
    {
      "area": "SAN JUAN",
      "zone": "SAN JUAN PR 00925"
    },
    {
      "area": "SAN JUAN",
      "zone": "URB EL COMANDANTE"
    },
    {
      "area": "SAN JUAN",
      "zone": "URB SAN IGNACIO"
    },
    {
      "area": "SAN JUAN",
      "zone": "URB SIERRA DEL RIO"
    },
    {
      "area": "SAN JUAN",
      "zone": "Urb. San Juan Gardens"
    },
    {
      "area": "SAN JUAN",
      "zone": "Urb. Villa Capri"
    }
  ],
  "SAN LORENZO": [],
  "SAN SEBASTIAN": [],
  "SAN SEBASTIÁN": [],
  "SANTA BARBARA": [],
  "SANTA ISABEL": [],
  "SANTURCE": [],
  "TOA ALTA": [],
  "TOA BAJA": [
    {
      "area": "TOA BAJA",
      "zone": "CANDELARIA"
    },
    {
      "area": "TOA BAJA",
      "zone": "URB LEVITTOWN"
    },
    {
      "area": "TOA BAJA",
      "zone": "URB LEVITTOWN LAKES"
    }
  ],
  "TRUJILLO ALTO": [
    {
      "area": "TRUJILLO ALTO",
      "zone": "BO LA GLORIA"
    },
    {
      "area": "TRUJILLO ALTO",
      "zone": "Bo. Saint Just"
    },
    {
      "area": "TRUJILLO ALTO",
      "zone": "CARRAIZO"
    }
  ],
  "UTUADO": [],
  "VEGA ALTA": [],
  "VEGA BAJA": [],
  "VIEQUES": [],
  "VILLALBA": [],
  "YABUCOA": [],
  "YAUCO": [],
  "timestamp_saved": "09/14/2023 05:41 PM"
}