{
  "ADJUNTAS": [
    {
      "area": "ADJUNTAS",
      "zone": "Bo. Juan Gonzalez #2"
    },
    {
      "area": "ADJUNTAS",
      "zone": "Bo. Saltillo Cienaga"
    }
  ],
  "AGUADA": [
    {
      "area": "AGUADA",
      "zone": "BO ESPINAL/SECT HOYO FRIO"
    },
    {
      "area": "AGUADA",
      "zone": "Bo. Jaguey"
    }
  ],
  "AGUADILLA": [],
  "AGUAS BUENAS": [],
  "AIBONITO": [
    {
      "area": "AIBONITO",
      "zone": "Bo. Robles"
    }
  ],
  "ANASCO": [
    {
      "area": "ANASCO",
      "zone": "Barrio Caracol"
    },
    {
      "area": "ANASCO",
      "zone": "CERRO GORDO"
    }
  ],
  "ARECIBO": [
    {
      "area": "ARECIBO",
      "zone": "Bo. Dominguito"
    },
    {
      "area": "ARECIBO",
      "zone": "HOYO LOS SANTOS - URB REGIONAL"
    },
    {
      "area": "ARECIBO",
      "zone": "Urb. Regional"
    }
  ],
  "ARROYO": [
    {
      "area": "ARROYO",
      "zone": "GUASIMAS"
    }
  ],
  "AÑASCO": [],
  "BARCELONETA": [],
  "BARRANQUITAS": [],
  "BAYAMON": [
    {
      "area": "BAYAMON",
      "zone": "BO NUEVO"
    },
    {
      "area": "BAYAMON",
      "zone": "BO NUEVO / SECT LOPEZ"
    },
    {
      "area": "BAYAMON",
      "zone": "MINILLAS"
    },
    {
      "area": "BAYAMON",
      "zone": "Urb. Forest View"
    }
  ],
  "BAYAMÓN": [],
  "CABO ROJO": [],
  "CAGUAS": [],
  "CAMPANILLA": [],
  "CAMUY": [],
  "CANDELARIA": [],
  "CANDELARIA ARENAS": [],
  "CANOVANAS": [],
  "CANÓVANAS": [],
  "CAROLINA": [
    {
      "area": "CAROLINA",
      "zone": "URB VILLA CAROLINA"
    }
  ],
  "CATANO": [],
  "CATAÑO": [],
  "CAYEY": [
    {
      "area": "CAYEY",
      "zone": "ACUED LOS CARRASQUILLOS"
    },
    {
      "area": "CAYEY",
      "zone": "Bo. Cercadillo"
    }
  ],
  "CEIBA": [],
  "CIALES": [],
  "CIDRA": [
    {
      "area": "CIDRA",
      "zone": "BEATRIZ"
    },
    {
      "area": "CIDRA",
      "zone": "BO BEATRIZ"
    }
  ],
  "COAMO": [],
  "COCO": [],
  "COMERIO": [],
  "COMERÍO": [],
  "COROZAL": [
    {
      "area": "COROZAL",
      "zone": "BO.MANA"
    }
  ],
  "CULEBRA": [],
  "DORADO": [],
  "ESTANCIAS DE FLORIDA": [],
  "FAJARDO": [
    {
      "area": "FAJARDO",
      "zone": "EXT MELENDEZ"
    }
  ],
  "FLORIDA": [],
  "GUANICA": [],
  "GUAYAMA": [
    {
      "area": "GUAYAMA",
      "zone": "Bo. Carite"
    }
  ],
  "GUAYANILLA": [
    {
      "area": "GUAYANILLA",
      "zone": "URB SANTA MARIA"
    }
  ],
  "GUAYNABO": [
    {
      "area": "GUAYNABO",
      "zone": "Bo. Rio"
    },
    {
      "area": "GUAYNABO",
      "zone": "PUEBLO VIEJO"
    },
    {
      "area": "GUAYNABO",
      "zone": "RIO"
    }
  ],
  "GURABO": [],
  "GUÁNICA": [],
  "HATILLO": [],
  "HATO REY": [],
  "HORMIGUEROS": [],
  "HUMACAO": [],
  "INGENIO": [],
  "ISABEL SEGUNDA": [],
  "ISABELA": [
    {
      "area": "ISABELA",
      "zone": "Bo. Llanadas"
    }
  ],
  "JAYUYA": [],
  "JUANA DIAZ": [
    {
      "area": "JUANA DIAZ",
      "zone": "COL SANTI"
    }
  ],
  "JUANA DÍAZ": [],
  "JUNCOS": [
    {
      "area": "JUNCOS",
      "zone": "JARDS JUNCOS **R055**"
    }
  ],
  "LAJAS": [
    {
      "area": "LAJAS",
      "zone": "Bo. Candelaria"
    }
  ],
  "LARES": [],
  "LAS MARIAS": [
    {
      "area": "LAS MARIAS",
      "zone": "BO FURNIAS"
    },
    {
      "area": "LAS MARIAS",
      "zone": "Bo. La Pura Concepcion"
    }
  ],
  "LAS MARÍAS": [],
  "LAS PIEDRAS": [],
  "LEVITTOWN": [],
  "LOIZA": [],
  "LOÍZA": [],
  "LUQUILLO": [],
  "MANATI": [],
  "MANATÍ": [],
  "MARICAO": [],
  "MAUNABO": [],
  "MAYAGUEZ": [
    {
      "area": "MAYAGUEZ",
      "zone": "Bo. Aguilar"
    },
    {
      "area": "MAYAGUEZ",
      "zone": "LA QUINTA"
    }
  ],
  "MAYAGÜEZ": [],
  "MOCA": [
    {
      "area": "MOCA",
      "zone": "BO PLATA BZN 16245"
    },
    {
      "area": "MOCA",
      "zone": "ROCHA MAGUEYES, BARRA PANAPEN"
    }
  ],
  "MOROVIS": [],
  "NAGUABO": [
    {
      "area": "NAGUABO",
      "zone": "DUQUE"
    }
  ],
  "NARANJITO": [],
  "OROCOVIS": [
    {
      "area": "OROCOVIS",
      "zone": "Bo. Bermejas"
    },
    {
      "area": "OROCOVIS",
      "zone": "Bo. Gato"
    }
  ],
  "PAJAROS": [],
  "PATILLAS": [
    {
      "area": "PATILLAS",
      "zone": "Bo. Los Pollos Carr. 3"
    }
  ],
  "PENUELAS": [
    {
      "area": "PENUELAS"
    }
  ],
  "PEÑUELAS": [],
  "PONCE": [],
  "PUERTO NUEVO": [],
  "PUERTO REAL": [],
  "PUNTA SANTIAGO": [],
  "QUEBRADILLAS": [],
  "RINCON": [
    {
      "area": "RINCON",
      "zone": "Bo. Atalaya"
    }
  ],
  "RINCÓN": [],
  "RIO GRANDE": [
    {
      "area": "RIO GRANDE",
      "zone": "BO MOROVIS  HORIZONTE MAR"
    },
    {
      "area": "RIO GRANDE",
      "zone": "Bo. Guzman Abajo"
    }
  ],
  "RIO PIEDRAS": [],
  "RÍO GRANDE": [],
  "RÍO PIEDRAS": [],
  "SABANA GRANDE": [],
  "SABANA SECA": [],
  "SALINAS": [],
  "SAN ANTONIO": [],
  "SAN GERMAN": [
    {
      "area": "SAN GERMAN",
      "zone": "MINILLAS,CAMINO DAVID MENDEZ"
    }
  ],
  "SAN GERMÁN": [],
  "SAN ISIDRO": [],
  "SAN JUAN": [
    {
      "area": "SAN JUAN",
      "zone": "CAIMITO"
    },
    {
      "area": "SAN JUAN",
      "zone": "GOBERNADOR PIÑERO"
    },
    {
      "area": "SAN JUAN",
      "zone": "MONACILLO URBANO"
    },
    {
      "area": "SAN JUAN",
      "zone": "QUEBRADA ARENAS"
    },
    {
      "area": "SAN JUAN",
      "zone": "URB LA RIVIERA"
    }
  ],
  "SAN LORENZO": [
    {
      "area": "SAN LORENZO",
      "zone": "ESPINO"
    }
  ],
  "SAN SEBASTIAN": [
    {
      "area": "SAN SEBASTIAN",
      "zone": "Bo. Mirabales"
    },
    {
      "area": "SAN SEBASTIAN",
      "zone": "CULEBRINAS"
    }
  ],
  "SAN SEBASTIÁN": [],
  "SANTA BARBARA": [],
  "SANTA ISABEL": [
    {
      "area": "SANTA ISABEL",
      "zone": "PRADERAS DEL SUR F 16"
    }
  ],
  "SANTURCE": [],
  "TOA ALTA": [
    {
      "area": "TOA ALTA",
      "zone": "LAS ACEROLAS"
    }
  ],
  "TOA BAJA": [
    {
      "area": "TOA BAJA",
      "zone": "Urb. 4ta Levittown"
    }
  ],
  "TRUJILLO ALTO": [],
  "UTUADO": [
    {
      "area": "UTUADO",
      "zone": "BO VIVI ABAJO SECT LOS MENCHAC"
    },
    {
      "area": "UTUADO",
      "zone": "SALTO ABAJO"
    }
  ],
  "VEGA ALTA": [],
  "VEGA BAJA": [
    {
      "area": "VEGA BAJA",
      "zone": "PUGNADO AFUERA"
    }
  ],
  "VIEQUES": [],
  "VILLALBA": [
    {
      "area": "VILLALBA",
      "zone": "Bo. Hato Puerco Arriba"
    }
  ],
  "YABUCOA": [
    {
      "area": "YABUCOA",
      "zone": "Bo. Guayabota"
    }
  ],
  "YAUCO": [],
  "timestamp_saved": "08/31/2023 08:36 PM"
}