{
  "ADJUNTAS": [
    {
      "area": "ADJUNTAS",
      "zone": "BO PORTUGUEZ"
    },
    {
      "area": "ADJUNTAS",
      "zone": "SALTILLO VACAS SEC CIENEGA"
    }
  ],
  "AGUADA": [],
  "AGUADILLA": [],
  "AGUAS BUENAS": [
    {
      "area": "AGUAS BUENAS",
      "zone": "BAYAMONCITO/SECT VELAZQUEZ"
    },
    {
      "area": "AGUAS BUENAS",
      "zone": "CAMINO MUNICIPAL/BO MULITAS"
    }
  ],
  "AIBONITO": [],
  "ANASCO": [],
  "ARECIBO": [],
  "ARROYO": [],
  "AÑASCO": [],
  "BARCELONETA": [
    {
      "area": "BARCELONETA",
      "zone": "Bo. Garrochales"
    }
  ],
  "BARRANQUITAS": [],
  "BAYAMON": [],
  "BAYAMÓN": [],
  "CABO ROJO": [
    {
      "area": "CABO ROJO",
      "zone": "Bo. Miradero"
    }
  ],
  "CAGUAS": [
    {
      "area": "CAGUAS",
      "zone": "CAÑABONCITO"
    },
    {
      "area": "CAGUAS",
      "zone": "Urb. José Mercado"
    }
  ],
  "CAMPANILLA": [],
  "CAMUY": [
    {
      "area": "CAMUY",
      "zone": "BO QUEBRADA/SECT ECHEGARAY"
    }
  ],
  "CANDELARIA": [],
  "CANDELARIA ARENAS": [],
  "CANOVANAS": [
    {
      "area": "CANOVANAS",
      "zone": "Bo. Campo Rico"
    }
  ],
  "CANÓVANAS": [],
  "CAROLINA": [],
  "CATANO": [],
  "CATAÑO": [],
  "CAYEY": [
    {
      "area": "CAYEY",
      "zone": "CAYEY"
    }
  ],
  "CEIBA": [],
  "CIALES": [],
  "CIDRA": [],
  "COAMO": [],
  "COCO": [],
  "COMERIO": [],
  "COMERÍO": [],
  "COROZAL": [],
  "CULEBRA": [],
  "DORADO": [],
  "ESTANCIAS DE FLORIDA": [],
  "FAJARDO": [],
  "FLORIDA": [],
  "GUANICA": [],
  "GUAYAMA": [
    {
      "area": "GUAYAMA",
      "zone": "COL GERARDO"
    }
  ],
  "GUAYANILLA": [
    {
      "area": "GUAYANILLA",
      "zone": "QUEBRADAS LA CAPITAL"
    }
  ],
  "GUAYNABO": [
    {
      "area": "GUAYNABO",
      "zone": "RIO"
    }
  ],
  "GURABO": [
    {
      "area": "GURABO",
      "zone": "Bo. Navarro"
    }
  ],
  "GUÁNICA": [],
  "HATILLO": [
    {
      "area": "HATILLO",
      "zone": "SECTOR LA LINEA ANEXO TULIPANE"
    }
  ],
  "HATO REY": [],
  "HORMIGUEROS": [],
  "HUMACAO": [
    {
      "area": "HUMACAO",
      "zone": "MAMBICHE"
    }
  ],
  "INGENIO": [],
  "ISABEL SEGUNDA": [],
  "ISABELA": [],
  "JAYUYA": [
    {
      "area": "JAYUYA",
      "zone": "Bo. Mameyes Arriba"
    }
  ],
  "JUANA DIAZ": [
    {
      "area": "JUANA DIAZ",
      "zone": "BO. RIO CAÑAS ABAJO"
    }
  ],
  "JUANA DÍAZ": [],
  "JUNCOS": [
    {
      "area": "JUNCOS",
      "zone": "VALEN ABAJO/LOS GOYTIA"
    }
  ],
  "LAJAS": [],
  "LARES": [],
  "LAS MARIAS": [
    {
      "area": "LAS MARIAS",
      "zone": "Sector Santa Rosa"
    }
  ],
  "LAS MARÍAS": [],
  "LAS PIEDRAS": [
    {
      "area": "LAS PIEDRAS",
      "zone": "BO TEJAS                 26052"
    },
    {
      "area": "LAS PIEDRAS",
      "zone": "Bo. Tejas"
    }
  ],
  "LEVITTOWN": [],
  "LOIZA": [],
  "LOÍZA": [],
  "LUQUILLO": [],
  "MANATI": [],
  "MANATÍ": [],
  "MARICAO": [],
  "MAUNABO": [],
  "MAYAGUEZ": [],
  "MAYAGÜEZ": [],
  "MOCA": [],
  "MOROVIS": [],
  "NAGUABO": [],
  "NARANJITO": [
    {
      "area": "NARANJITO",
      "zone": "BO ACHIOTE SEC LA MARAVILLA"
    },
    {
      "area": "NARANJITO",
      "zone": "BO LOMAS CENTRO"
    }
  ],
  "OROCOVIS": [
    {
      "area": "OROCOVIS",
      "zone": "Bo. Pellejas 2"
    },
    {
      "area": "OROCOVIS",
      "zone": "OROCOVIS"
    }
  ],
  "PAJAROS": [],
  "PATILLAS": [],
  "PENUELAS": [],
  "PEÑUELAS": [],
  "PONCE": [
    {
      "area": "PONCE",
      "zone": "CANAS URBANO"
    },
    {
      "area": "PONCE",
      "zone": "CUARTO"
    },
    {
      "area": "PONCE",
      "zone": "PLAYA DE PONCE"
    },
    {
      "area": "PONCE",
      "zone": "URB RIBERAS DEL BUCANA"
    },
    {
      "area": "PONCE",
      "zone": "Urb. El Bosque"
    }
  ],
  "PUERTO NUEVO": [],
  "PUERTO REAL": [],
  "PUNTA SANTIAGO": [],
  "QUEBRADILLAS": [],
  "RINCON": [],
  "RINCÓN": [],
  "RIO GRANDE": [],
  "RIO PIEDRAS": [],
  "RÍO GRANDE": [],
  "RÍO PIEDRAS": [],
  "SABANA GRANDE": [],
  "SABANA SECA": [],
  "SALINAS": [
    {
      "area": "SALINAS",
      "zone": "Albergue Olimpico"
    }
  ],
  "SAN ANTONIO": [],
  "SAN GERMAN": [
    {
      "area": "SAN GERMAN",
      "zone": "MINILLAS"
    },
    {
      "area": "SAN GERMAN",
      "zone": "PLAZA DEL OESTE STORE 156"
    }
  ],
  "SAN GERMÁN": [],
  "SAN ISIDRO": [],
  "SAN JUAN": [
    {
      "area": "SAN JUAN",
      "zone": "Bo. Cupey Alto"
    },
    {
      "area": "SAN JUAN",
      "zone": "Bo. Punta Las Marias"
    },
    {
      "area": "SAN JUAN",
      "zone": "CARRAIZO ALTO EL MUDO R SALDAN"
    },
    {
      "area": "SAN JUAN",
      "zone": "COND CAMINOS DEL BOSQUE"
    },
    {
      "area": "SAN JUAN",
      "zone": "ESQ PAOLI BASE 3"
    },
    {
      "area": "SAN JUAN",
      "zone": "HATO REY NORTE"
    },
    {
      "area": "SAN JUAN",
      "zone": "URB VILLA GRANADA"
    },
    {
      "area": "SAN JUAN",
      "zone": "Urb. Hyde Park"
    }
  ],
  "SAN LORENZO": [
    {
      "area": "SAN LORENZO",
      "zone": "Bo. Jagual"
    },
    {
      "area": "SAN LORENZO",
      "zone": "Sector Quebrada Arenas"
    }
  ],
  "SAN SEBASTIAN": [],
  "SAN SEBASTIÁN": [],
  "SANTA BARBARA": [],
  "SANTA ISABEL": [],
  "SANTURCE": [],
  "TOA ALTA": [
    {
      "area": "TOA ALTA",
      "zone": "QUEBRADA CRUZ  EL CUCO"
    }
  ],
  "TOA BAJA": [
    {
      "area": "TOA BAJA",
      "zone": "Urb. 2da Levittown"
    }
  ],
  "TRUJILLO ALTO": [
    {
      "area": "TRUJILLO ALTO",
      "zone": "Bo. Las Cuevas"
    }
  ],
  "UTUADO": [],
  "VEGA ALTA": [],
  "VEGA BAJA": [],
  "VIEQUES": [],
  "VILLALBA": [],
  "YABUCOA": [],
  "YAUCO": [],
  "timestamp_saved": "10/23/2023 09:01 PM"
}