{
  "regions": [
    {
      "name": "Arecibo",
      "percentageClientsWithService": 100.0,
      "percentageClientsWithoutService": 0.0,
      "totalClients": 177369,
      "totalClientsWithService": 177367,
      "totalClientsWithoutService": 2
    },
    {
      "name": "Bayamon",
      "percentageClientsWithService": 99.8,
      "percentageClientsWithoutService": 0.2,
      "totalClients": 216496,
      "totalClientsWithService": 216070,
      "totalClientsWithoutService": 426
    },
    {
      "name": "Carolina",
      "percentageClientsWithService": 99.99,
      "percentageClientsWithoutService": 0.01,
      "totalClients": 141663,
      "totalClientsWithService": 141653,
      "totalClientsWithoutService": 10
    },
    {
      "name": "Caguas",
      "percentageClientsWithService": 99.44,
      "percentageClientsWithoutService": 0.56,
      "totalClients": 250514,
      "totalClientsWithService": 249122,
      "totalClientsWithoutService": 1392
    },
    {
      "name": "Mayaguez",
      "percentageClientsWithService": 99.81,
      "percentageClientsWithoutService": 0.19,
      "totalClients": 216605,
      "totalClientsWithService": 216196,
      "totalClientsWithoutService": 409
    },
    {
      "name": "Ponce",
      "percentageClientsWithService": 100.0,
      "percentageClientsWithoutService": 0.0,
      "totalClients": 212508,
      "totalClientsWithService": 212498,
      "totalClientsWithoutService": 10
    },
    {
      "name": "San Juan",
      "percentageClientsWithService": 100.0,
      "percentageClientsWithoutService": 0.0,
      "totalClients": 253068,
      "totalClientsWithService": 253067,
      "totalClientsWithoutService": 1
    }
  ],
  "timestamp": "10/22/2023 06:55 PM",
  "timestamp_saved": "10/22/2023 10:55 PM",
  "totals": {
    "totalClients": 1468223,
    "totalClientsWithService": 1465973,
    "totalClientsWithoutService": 2250,
    "totalPercentageWithService": 99.85,
    "totalPercentageWithoutService": 0.15
  }
}