{
  "regions": [
    {
      "name": "Arecibo",
      "percentageClientsWithService": 99.28,
      "percentageClientsWithoutService": 0.72,
      "totalClients": 177369,
      "totalClientsWithService": 176093,
      "totalClientsWithoutService": 1276
    },
    {
      "name": "Bayamon",
      "percentageClientsWithService": 99.01,
      "percentageClientsWithoutService": 0.99,
      "totalClients": 216496,
      "totalClientsWithService": 214359,
      "totalClientsWithoutService": 2137
    },
    {
      "name": "Carolina",
      "percentageClientsWithService": 99.99,
      "percentageClientsWithoutService": 0.01,
      "totalClients": 141663,
      "totalClientsWithService": 141648,
      "totalClientsWithoutService": 15
    },
    {
      "name": "Caguas",
      "percentageClientsWithService": 99.97,
      "percentageClientsWithoutService": 0.03,
      "totalClients": 250514,
      "totalClientsWithService": 250438,
      "totalClientsWithoutService": 76
    },
    {
      "name": "Mayaguez",
      "percentageClientsWithService": 99.02,
      "percentageClientsWithoutService": 0.98,
      "totalClients": 216605,
      "totalClientsWithService": 214474,
      "totalClientsWithoutService": 2131
    },
    {
      "name": "Ponce",
      "percentageClientsWithService": 99.94,
      "percentageClientsWithoutService": 0.06,
      "totalClients": 212508,
      "totalClientsWithService": 212380,
      "totalClientsWithoutService": 128
    },
    {
      "name": "San Juan",
      "percentageClientsWithService": 99.09,
      "percentageClientsWithoutService": 0.91,
      "totalClients": 253068,
      "totalClientsWithService": 250773,
      "totalClientsWithoutService": 2295
    }
  ],
  "timestamp": "10/28/2023 05:55 PM",
  "timestamp_saved": "10/28/2023 09:55 PM",
  "totals": {
    "totalClients": 1468223,
    "totalClientsWithService": 1460165,
    "totalClientsWithoutService": 8058,
    "totalPercentageWithService": 99.45,
    "totalPercentageWithoutService": 0.55
  }
}