{
  "regions": [
    {
      "name": "Arecibo",
      "percentageClientsWithService": 98.2,
      "percentageClientsWithoutService": 1.8,
      "totalClients": 177369,
      "totalClientsWithService": 174179,
      "totalClientsWithoutService": 3190
    },
    {
      "name": "Bayamon",
      "percentageClientsWithService": 99.79,
      "percentageClientsWithoutService": 0.21,
      "totalClients": 216496,
      "totalClientsWithService": 216041,
      "totalClientsWithoutService": 455
    },
    {
      "name": "Carolina",
      "percentageClientsWithService": 99.99,
      "percentageClientsWithoutService": 0.01,
      "totalClients": 141663,
      "totalClientsWithService": 141646,
      "totalClientsWithoutService": 17
    },
    {
      "name": "Caguas",
      "percentageClientsWithService": 99.65,
      "percentageClientsWithoutService": 0.35,
      "totalClients": 250514,
      "totalClientsWithService": 249647,
      "totalClientsWithoutService": 867
    },
    {
      "name": "Mayaguez",
      "percentageClientsWithService": 98.34,
      "percentageClientsWithoutService": 1.66,
      "totalClients": 216605,
      "totalClientsWithService": 213016,
      "totalClientsWithoutService": 3589
    },
    {
      "name": "Ponce",
      "percentageClientsWithService": 99.98,
      "percentageClientsWithoutService": 0.02,
      "totalClients": 212508,
      "totalClientsWithService": 212473,
      "totalClientsWithoutService": 35
    },
    {
      "name": "San Juan",
      "percentageClientsWithService": 99.08,
      "percentageClientsWithoutService": 0.92,
      "totalClients": 253068,
      "totalClientsWithService": 250736,
      "totalClientsWithoutService": 2332
    }
  ],
  "timestamp": "10/26/2023 05:40 PM",
  "timestamp_saved": "10/26/2023 09:40 PM",
  "totals": {
    "totalClients": 1468223,
    "totalClientsWithService": 1457738,
    "totalClientsWithoutService": 10485,
    "totalPercentageWithService": 99.29,
    "totalPercentageWithoutService": 0.71
  }
}