{
  "regions": [
    {
      "name": "Arecibo",
      "percentageClientsWithService": 99.11,
      "percentageClientsWithoutService": 0.89,
      "totalClients": 177369,
      "totalClientsWithService": 175794,
      "totalClientsWithoutService": 1575
    },
    {
      "name": "Bayamon",
      "percentageClientsWithService": 99.24,
      "percentageClientsWithoutService": 0.76,
      "totalClients": 216496,
      "totalClientsWithService": 214850,
      "totalClientsWithoutService": 1646
    },
    {
      "name": "Carolina",
      "percentageClientsWithService": 94.61,
      "percentageClientsWithoutService": 5.39,
      "totalClients": 141663,
      "totalClientsWithService": 134031,
      "totalClientsWithoutService": 7632
    },
    {
      "name": "Caguas",
      "percentageClientsWithService": 99.94,
      "percentageClientsWithoutService": 0.06,
      "totalClients": 250514,
      "totalClientsWithService": 250375,
      "totalClientsWithoutService": 139
    },
    {
      "name": "Mayaguez",
      "percentageClientsWithService": 99.86,
      "percentageClientsWithoutService": 0.14,
      "totalClients": 216605,
      "totalClientsWithService": 216305,
      "totalClientsWithoutService": 300
    },
    {
      "name": "Ponce",
      "percentageClientsWithService": 99.98,
      "percentageClientsWithoutService": 0.02,
      "totalClients": 212508,
      "totalClientsWithService": 212455,
      "totalClientsWithoutService": 53
    },
    {
      "name": "San Juan",
      "percentageClientsWithService": 99.67,
      "percentageClientsWithoutService": 0.33,
      "totalClients": 253068,
      "totalClientsWithService": 252244,
      "totalClientsWithoutService": 824
    }
  ],
  "timestamp": "08/05/2023 08:40 PM",
  "timestamp_saved": "08/06/2023 12:40 AM",
  "totals": {
    "totalClients": 1468223,
    "totalClientsWithService": 1456054,
    "totalClientsWithoutService": 12169,
    "totalPercentageWithService": 99.17,
    "totalPercentageWithoutService": 0.83
  }
}