{
  "regions": [
    {
      "name": "Arecibo",
      "percentageClientsWithService": 99.05,
      "percentageClientsWithoutService": 0.95,
      "totalClients": 177369,
      "totalClientsWithService": 175677,
      "totalClientsWithoutService": 1692
    },
    {
      "name": "Bayamon",
      "percentageClientsWithService": 99.74,
      "percentageClientsWithoutService": 0.26,
      "totalClients": 216496,
      "totalClientsWithService": 215937,
      "totalClientsWithoutService": 559
    },
    {
      "name": "Carolina",
      "percentageClientsWithService": 99.81,
      "percentageClientsWithoutService": 0.19,
      "totalClients": 141663,
      "totalClientsWithService": 141388,
      "totalClientsWithoutService": 275
    },
    {
      "name": "Caguas",
      "percentageClientsWithService": 99.38,
      "percentageClientsWithoutService": 0.62,
      "totalClients": 250514,
      "totalClientsWithService": 248959,
      "totalClientsWithoutService": 1555
    },
    {
      "name": "Mayaguez",
      "percentageClientsWithService": 99.95,
      "percentageClientsWithoutService": 0.05,
      "totalClients": 216605,
      "totalClientsWithService": 216492,
      "totalClientsWithoutService": 113
    },
    {
      "name": "Ponce",
      "percentageClientsWithService": 99.97,
      "percentageClientsWithoutService": 0.03,
      "totalClients": 212508,
      "totalClientsWithService": 212435,
      "totalClientsWithoutService": 73
    },
    {
      "name": "San Juan",
      "percentageClientsWithService": 99.88,
      "percentageClientsWithoutService": 0.12,
      "totalClients": 253068,
      "totalClientsWithService": 252770,
      "totalClientsWithoutService": 298
    }
  ],
  "timestamp": "07/26/2023 07:50 PM",
  "timestamp_saved": "07/26/2023 11:50 PM",
  "totals": {
    "totalClients": 1468223,
    "totalClientsWithService": 1463658,
    "totalClientsWithoutService": 4565,
    "totalPercentageWithService": 99.69,
    "totalPercentageWithoutService": 0.31
  }
}