{
  "regions": [
    {
      "name": "Arecibo",
      "percentageClientsWithService": 99.99,
      "percentageClientsWithoutService": 0.01,
      "totalClients": 177369,
      "totalClientsWithService": 177353,
      "totalClientsWithoutService": 16
    },
    {
      "name": "Bayamon",
      "percentageClientsWithService": 99.63,
      "percentageClientsWithoutService": 0.37,
      "totalClients": 216496,
      "totalClientsWithService": 215695,
      "totalClientsWithoutService": 801
    },
    {
      "name": "Carolina",
      "percentageClientsWithService": 99.95,
      "percentageClientsWithoutService": 0.05,
      "totalClients": 141663,
      "totalClientsWithService": 141592,
      "totalClientsWithoutService": 71
    },
    {
      "name": "Caguas",
      "percentageClientsWithService": 99.83,
      "percentageClientsWithoutService": 0.17,
      "totalClients": 250514,
      "totalClientsWithService": 250085,
      "totalClientsWithoutService": 429
    },
    {
      "name": "Mayaguez",
      "percentageClientsWithService": 92.49,
      "percentageClientsWithoutService": 7.51,
      "totalClients": 216605,
      "totalClientsWithService": 200330,
      "totalClientsWithoutService": 16275
    },
    {
      "name": "Ponce",
      "percentageClientsWithService": 98.5,
      "percentageClientsWithoutService": 1.5,
      "totalClients": 212508,
      "totalClientsWithService": 209318,
      "totalClientsWithoutService": 3190
    },
    {
      "name": "San Juan",
      "percentageClientsWithService": 98.93,
      "percentageClientsWithoutService": 1.07,
      "totalClients": 253068,
      "totalClientsWithService": 250353,
      "totalClientsWithoutService": 2715
    }
  ],
  "timestamp": "09/08/2023 09:00 PM",
  "timestamp_saved": "09/09/2023 01:00 AM",
  "totals": {
    "totalClients": 1468223,
    "totalClientsWithService": 1444726,
    "totalClientsWithoutService": 23497,
    "totalPercentageWithService": 98.4,
    "totalPercentageWithoutService": 1.6
  }
}