{
  "regions": [
    {
      "name": "Arecibo",
      "percentageClientsWithService": 97.86,
      "percentageClientsWithoutService": 2.14,
      "totalClients": 177369,
      "totalClientsWithService": 173565,
      "totalClientsWithoutService": 3804
    },
    {
      "name": "Bayamon",
      "percentageClientsWithService": 99.96,
      "percentageClientsWithoutService": 0.04,
      "totalClients": 216496,
      "totalClientsWithService": 216402,
      "totalClientsWithoutService": 94
    },
    {
      "name": "Carolina",
      "percentageClientsWithService": 99.6,
      "percentageClientsWithoutService": 0.4,
      "totalClients": 141663,
      "totalClientsWithService": 141097,
      "totalClientsWithoutService": 566
    },
    {
      "name": "Caguas",
      "percentageClientsWithService": 99.08,
      "percentageClientsWithoutService": 0.92,
      "totalClients": 250514,
      "totalClientsWithService": 248198,
      "totalClientsWithoutService": 2316
    },
    {
      "name": "Mayaguez",
      "percentageClientsWithService": 99.25,
      "percentageClientsWithoutService": 0.75,
      "totalClients": 216605,
      "totalClientsWithService": 214975,
      "totalClientsWithoutService": 1630
    },
    {
      "name": "Ponce",
      "percentageClientsWithService": 95.99,
      "percentageClientsWithoutService": 4.01,
      "totalClients": 212508,
      "totalClientsWithService": 203986,
      "totalClientsWithoutService": 8522
    },
    {
      "name": "San Juan",
      "percentageClientsWithService": 99.99,
      "percentageClientsWithoutService": 0.01,
      "totalClients": 253068,
      "totalClientsWithService": 253035,
      "totalClientsWithoutService": 33
    }
  ],
  "timestamp": "08/26/2023 09:55 AM",
  "timestamp_saved": "08/26/2023 01:55 PM",
  "totals": {
    "totalClients": 1468223,
    "totalClientsWithService": 1451258,
    "totalClientsWithoutService": 16965,
    "totalPercentageWithService": 98.84,
    "totalPercentageWithoutService": 1.16
  }
}