{
  "regions": [
    {
      "name": "Arecibo",
      "percentageClientsWithService": 99.97,
      "percentageClientsWithoutService": 0.03,
      "totalClients": 177369,
      "totalClientsWithService": 177311,
      "totalClientsWithoutService": 58
    },
    {
      "name": "Bayamon",
      "percentageClientsWithService": 99.43,
      "percentageClientsWithoutService": 0.57,
      "totalClients": 216496,
      "totalClientsWithService": 215256,
      "totalClientsWithoutService": 1240
    },
    {
      "name": "Carolina",
      "percentageClientsWithService": 99.6,
      "percentageClientsWithoutService": 0.4,
      "totalClients": 141663,
      "totalClientsWithService": 141101,
      "totalClientsWithoutService": 562
    },
    {
      "name": "Caguas",
      "percentageClientsWithService": 99.77,
      "percentageClientsWithoutService": 0.23,
      "totalClients": 250514,
      "totalClientsWithService": 249942,
      "totalClientsWithoutService": 572
    },
    {
      "name": "Mayaguez",
      "percentageClientsWithService": 99.98,
      "percentageClientsWithoutService": 0.02,
      "totalClients": 216605,
      "totalClientsWithService": 216559,
      "totalClientsWithoutService": 46
    },
    {
      "name": "Ponce",
      "percentageClientsWithService": 99.92,
      "percentageClientsWithoutService": 0.08,
      "totalClients": 212508,
      "totalClientsWithService": 212335,
      "totalClientsWithoutService": 173
    },
    {
      "name": "San Juan",
      "percentageClientsWithService": 99.79,
      "percentageClientsWithoutService": 0.21,
      "totalClients": 253068,
      "totalClientsWithService": 252544,
      "totalClientsWithoutService": 524
    }
  ],
  "timestamp": "08/08/2023 05:30 AM",
  "timestamp_saved": "08/08/2023 09:30 AM",
  "totals": {
    "totalClients": 1468223,
    "totalClientsWithService": 1465048,
    "totalClientsWithoutService": 3175,
    "totalPercentageWithService": 99.78,
    "totalPercentageWithoutService": 0.22
  }
}