{
  "regions": [
    {
      "name": "Arecibo",
      "percentageClientsWithService": 99.53,
      "percentageClientsWithoutService": 0.47,
      "totalClients": 177369,
      "totalClientsWithService": 176543,
      "totalClientsWithoutService": 826
    },
    {
      "name": "Bayamon",
      "percentageClientsWithService": 99.7,
      "percentageClientsWithoutService": 0.3,
      "totalClients": 216496,
      "totalClientsWithService": 215857,
      "totalClientsWithoutService": 639
    },
    {
      "name": "Carolina",
      "percentageClientsWithService": 99.98,
      "percentageClientsWithoutService": 0.02,
      "totalClients": 141663,
      "totalClientsWithService": 141641,
      "totalClientsWithoutService": 22
    },
    {
      "name": "Caguas",
      "percentageClientsWithService": 99.98,
      "percentageClientsWithoutService": 0.02,
      "totalClients": 250514,
      "totalClientsWithService": 250458,
      "totalClientsWithoutService": 56
    },
    {
      "name": "Mayaguez",
      "percentageClientsWithService": 98.73,
      "percentageClientsWithoutService": 1.27,
      "totalClients": 216605,
      "totalClientsWithService": 213853,
      "totalClientsWithoutService": 2752
    },
    {
      "name": "Ponce",
      "percentageClientsWithService": 99.74,
      "percentageClientsWithoutService": 0.26,
      "totalClients": 212508,
      "totalClientsWithService": 211965,
      "totalClientsWithoutService": 543
    },
    {
      "name": "San Juan",
      "percentageClientsWithService": 99.82,
      "percentageClientsWithoutService": 0.18,
      "totalClients": 253068,
      "totalClientsWithService": 252608,
      "totalClientsWithoutService": 460
    }
  ],
  "timestamp": "08/15/2023 09:30 PM",
  "timestamp_saved": "08/16/2023 01:30 AM",
  "totals": {
    "totalClients": 1468223,
    "totalClientsWithService": 1462925,
    "totalClientsWithoutService": 5298,
    "totalPercentageWithService": 99.64,
    "totalPercentageWithoutService": 0.36
  }
}