{
  "regions": [
    {
      "name": "Arecibo",
      "percentageClientsWithService": 99.94,
      "percentageClientsWithoutService": 0.06,
      "totalClients": 177369,
      "totalClientsWithService": 177254,
      "totalClientsWithoutService": 115
    },
    {
      "name": "Bayamon",
      "percentageClientsWithService": 99.56,
      "percentageClientsWithoutService": 0.44,
      "totalClients": 216496,
      "totalClientsWithService": 215538,
      "totalClientsWithoutService": 958
    },
    {
      "name": "Carolina",
      "percentageClientsWithService": 98.48,
      "percentageClientsWithoutService": 1.52,
      "totalClients": 141663,
      "totalClientsWithService": 139512,
      "totalClientsWithoutService": 2151
    },
    {
      "name": "Caguas",
      "percentageClientsWithService": 99.72,
      "percentageClientsWithoutService": 0.28,
      "totalClients": 250514,
      "totalClientsWithService": 249819,
      "totalClientsWithoutService": 695
    },
    {
      "name": "Mayaguez",
      "percentageClientsWithService": 99.84,
      "percentageClientsWithoutService": 0.16,
      "totalClients": 216605,
      "totalClientsWithService": 216254,
      "totalClientsWithoutService": 351
    },
    {
      "name": "Ponce",
      "percentageClientsWithService": 99.61,
      "percentageClientsWithoutService": 0.39,
      "totalClients": 212508,
      "totalClientsWithService": 211684,
      "totalClientsWithoutService": 824
    },
    {
      "name": "San Juan",
      "percentageClientsWithService": 99.71,
      "percentageClientsWithoutService": 0.29,
      "totalClients": 253068,
      "totalClientsWithService": 252325,
      "totalClientsWithoutService": 743
    }
  ],
  "timestamp": "10/27/2023 02:05 PM",
  "timestamp_saved": "10/27/2023 06:05 PM",
  "totals": {
    "totalClients": 1468223,
    "totalClientsWithService": 1462386,
    "totalClientsWithoutService": 5837,
    "totalPercentageWithService": 99.6,
    "totalPercentageWithoutService": 0.4
  }
}