{
  "regions": [
    {
      "name": "Arecibo",
      "percentageClientsWithService": 98.9,
      "percentageClientsWithoutService": 1.1,
      "totalClients": 177369,
      "totalClientsWithService": 175419,
      "totalClientsWithoutService": 1950
    },
    {
      "name": "Bayamon",
      "percentageClientsWithService": 99.69,
      "percentageClientsWithoutService": 0.31,
      "totalClients": 216496,
      "totalClientsWithService": 215826,
      "totalClientsWithoutService": 670
    },
    {
      "name": "Carolina",
      "percentageClientsWithService": 100.0,
      "percentageClientsWithoutService": 0.0,
      "totalClients": 141663,
      "totalClientsWithService": 141659,
      "totalClientsWithoutService": 4
    },
    {
      "name": "Caguas",
      "percentageClientsWithService": 98.84,
      "percentageClientsWithoutService": 1.16,
      "totalClients": 250514,
      "totalClientsWithService": 247613,
      "totalClientsWithoutService": 2901
    },
    {
      "name": "Mayaguez",
      "percentageClientsWithService": 99.35,
      "percentageClientsWithoutService": 0.65,
      "totalClients": 216605,
      "totalClientsWithService": 215200,
      "totalClientsWithoutService": 1405
    },
    {
      "name": "Ponce",
      "percentageClientsWithService": 99.97,
      "percentageClientsWithoutService": 0.03,
      "totalClients": 212508,
      "totalClientsWithService": 212444,
      "totalClientsWithoutService": 64
    },
    {
      "name": "San Juan",
      "percentageClientsWithService": 99.94,
      "percentageClientsWithoutService": 0.06,
      "totalClients": 253068,
      "totalClientsWithService": 252905,
      "totalClientsWithoutService": 163
    }
  ],
  "timestamp": "09/25/2023 09:20 AM",
  "timestamp_saved": "09/25/2023 01:20 PM",
  "totals": {
    "totalClients": 1468223,
    "totalClientsWithService": 1461066,
    "totalClientsWithoutService": 7157,
    "totalPercentageWithService": 99.51,
    "totalPercentageWithoutService": 0.49
  }
}