{
  "regions": [
    {
      "name": "Arecibo",
      "percentageClientsWithService": 99.98,
      "percentageClientsWithoutService": 0.02,
      "totalClients": 177369,
      "totalClientsWithService": 177327,
      "totalClientsWithoutService": 42
    },
    {
      "name": "Bayamon",
      "percentageClientsWithService": 99.85,
      "percentageClientsWithoutService": 0.15,
      "totalClients": 216496,
      "totalClientsWithService": 216182,
      "totalClientsWithoutService": 314
    },
    {
      "name": "Carolina",
      "percentageClientsWithService": 100.0,
      "percentageClientsWithoutService": 0.0,
      "totalClients": 141663,
      "totalClientsWithService": 141663,
      "totalClientsWithoutService": 0
    },
    {
      "name": "Caguas",
      "percentageClientsWithService": 99.16,
      "percentageClientsWithoutService": 0.84,
      "totalClients": 250514,
      "totalClientsWithService": 248406,
      "totalClientsWithoutService": 2108
    },
    {
      "name": "Mayaguez",
      "percentageClientsWithService": 99.8,
      "percentageClientsWithoutService": 0.2,
      "totalClients": 216605,
      "totalClientsWithService": 216161,
      "totalClientsWithoutService": 444
    },
    {
      "name": "Ponce",
      "percentageClientsWithService": 97.16,
      "percentageClientsWithoutService": 2.84,
      "totalClients": 212508,
      "totalClientsWithService": 206479,
      "totalClientsWithoutService": 6029
    },
    {
      "name": "San Juan",
      "percentageClientsWithService": 99.9,
      "percentageClientsWithoutService": 0.1,
      "totalClients": 253068,
      "totalClientsWithService": 252805,
      "totalClientsWithoutService": 263
    }
  ],
  "timestamp": "10/18/2023 01:20 AM",
  "timestamp_saved": "10/18/2023 05:20 AM",
  "totals": {
    "totalClients": 1468223,
    "totalClientsWithService": 1459023,
    "totalClientsWithoutService": 9200,
    "totalPercentageWithService": 99.37,
    "totalPercentageWithoutService": 0.63
  }
}