{
  "regions": [
    {
      "name": "Arecibo",
      "percentageClientsWithService": 99.98,
      "percentageClientsWithoutService": 0.02,
      "totalClients": 177369,
      "totalClientsWithService": 177342,
      "totalClientsWithoutService": 27
    },
    {
      "name": "Bayamon",
      "percentageClientsWithService": 99.88,
      "percentageClientsWithoutService": 0.12,
      "totalClients": 216496,
      "totalClientsWithService": 216235,
      "totalClientsWithoutService": 261
    },
    {
      "name": "Carolina",
      "percentageClientsWithService": 99.85,
      "percentageClientsWithoutService": 0.15,
      "totalClients": 141663,
      "totalClientsWithService": 141449,
      "totalClientsWithoutService": 214
    },
    {
      "name": "Caguas",
      "percentageClientsWithService": 99.88,
      "percentageClientsWithoutService": 0.12,
      "totalClients": 250514,
      "totalClientsWithService": 250207,
      "totalClientsWithoutService": 307
    },
    {
      "name": "Mayaguez",
      "percentageClientsWithService": 97.98,
      "percentageClientsWithoutService": 2.02,
      "totalClients": 216605,
      "totalClientsWithService": 212232,
      "totalClientsWithoutService": 4373
    },
    {
      "name": "Ponce",
      "percentageClientsWithService": 99.74,
      "percentageClientsWithoutService": 0.26,
      "totalClients": 212508,
      "totalClientsWithService": 211961,
      "totalClientsWithoutService": 547
    },
    {
      "name": "San Juan",
      "percentageClientsWithService": 99.69,
      "percentageClientsWithoutService": 0.31,
      "totalClients": 253068,
      "totalClientsWithService": 252296,
      "totalClientsWithoutService": 772
    }
  ],
  "timestamp": "09/04/2023 10:00 AM",
  "timestamp_saved": "09/04/2023 02:00 PM",
  "totals": {
    "totalClients": 1468223,
    "totalClientsWithService": 1461722,
    "totalClientsWithoutService": 6501,
    "totalPercentageWithService": 99.56,
    "totalPercentageWithoutService": 0.44
  }
}