{
  "regions": [
    {
      "name": "Arecibo",
      "percentageClientsWithService": 99.98,
      "percentageClientsWithoutService": 0.02,
      "totalClients": 177369,
      "totalClientsWithService": 177341,
      "totalClientsWithoutService": 28
    },
    {
      "name": "Bayamon",
      "percentageClientsWithService": 99.95,
      "percentageClientsWithoutService": 0.05,
      "totalClients": 216496,
      "totalClientsWithService": 216390,
      "totalClientsWithoutService": 106
    },
    {
      "name": "Carolina",
      "percentageClientsWithService": 99.93,
      "percentageClientsWithoutService": 0.07,
      "totalClients": 141663,
      "totalClientsWithService": 141557,
      "totalClientsWithoutService": 106
    },
    {
      "name": "Caguas",
      "percentageClientsWithService": 99.93,
      "percentageClientsWithoutService": 0.07,
      "totalClients": 250514,
      "totalClientsWithService": 250340,
      "totalClientsWithoutService": 174
    },
    {
      "name": "Mayaguez",
      "percentageClientsWithService": 99.39,
      "percentageClientsWithoutService": 0.61,
      "totalClients": 216605,
      "totalClientsWithService": 215293,
      "totalClientsWithoutService": 1312
    },
    {
      "name": "Ponce",
      "percentageClientsWithService": 99.94,
      "percentageClientsWithoutService": 0.06,
      "totalClients": 212508,
      "totalClientsWithService": 212381,
      "totalClientsWithoutService": 127
    },
    {
      "name": "San Juan",
      "percentageClientsWithService": 99.17,
      "percentageClientsWithoutService": 0.83,
      "totalClients": 253068,
      "totalClientsWithService": 250966,
      "totalClientsWithoutService": 2102
    }
  ],
  "timestamp": "10/18/2023 06:45 PM",
  "timestamp_saved": "10/18/2023 10:45 PM",
  "totals": {
    "totalClients": 1468223,
    "totalClientsWithService": 1464268,
    "totalClientsWithoutService": 3955,
    "totalPercentageWithService": 99.73,
    "totalPercentageWithoutService": 0.27
  }
}