{
  "regions": [
    {
      "name": "Arecibo",
      "percentageClientsWithService": 99.94,
      "percentageClientsWithoutService": 0.06,
      "totalClients": 177369,
      "totalClientsWithService": 177254,
      "totalClientsWithoutService": 115
    },
    {
      "name": "Bayamon",
      "percentageClientsWithService": 99.63,
      "percentageClientsWithoutService": 0.37,
      "totalClients": 216496,
      "totalClientsWithService": 215692,
      "totalClientsWithoutService": 804
    },
    {
      "name": "Carolina",
      "percentageClientsWithService": 99.92,
      "percentageClientsWithoutService": 0.08,
      "totalClients": 141663,
      "totalClientsWithService": 141545,
      "totalClientsWithoutService": 118
    },
    {
      "name": "Caguas",
      "percentageClientsWithService": 99.74,
      "percentageClientsWithoutService": 0.26,
      "totalClients": 250514,
      "totalClientsWithService": 249859,
      "totalClientsWithoutService": 655
    },
    {
      "name": "Mayaguez",
      "percentageClientsWithService": 99.75,
      "percentageClientsWithoutService": 0.25,
      "totalClients": 216605,
      "totalClientsWithService": 216059,
      "totalClientsWithoutService": 546
    },
    {
      "name": "Ponce",
      "percentageClientsWithService": 99.79,
      "percentageClientsWithoutService": 0.21,
      "totalClients": 212508,
      "totalClientsWithService": 212059,
      "totalClientsWithoutService": 449
    },
    {
      "name": "San Juan",
      "percentageClientsWithService": 99.89,
      "percentageClientsWithoutService": 0.11,
      "totalClients": 253068,
      "totalClientsWithService": 252787,
      "totalClientsWithoutService": 281
    }
  ],
  "timestamp": "08/22/2023 06:55 AM",
  "timestamp_saved": "08/22/2023 10:55 AM",
  "totals": {
    "totalClients": 1468223,
    "totalClientsWithService": 1465255,
    "totalClientsWithoutService": 2968,
    "totalPercentageWithService": 99.8,
    "totalPercentageWithoutService": 0.2
  }
}