{
  "regions": [
    {
      "name": "Arecibo",
      "percentageClientsWithService": 99.76,
      "percentageClientsWithoutService": 0.24,
      "totalClients": 177369,
      "totalClientsWithService": 176943,
      "totalClientsWithoutService": 426
    },
    {
      "name": "Bayamon",
      "percentageClientsWithService": 99.98,
      "percentageClientsWithoutService": 0.02,
      "totalClients": 216496,
      "totalClientsWithService": 216463,
      "totalClientsWithoutService": 33
    },
    {
      "name": "Carolina",
      "percentageClientsWithService": 99.72,
      "percentageClientsWithoutService": 0.28,
      "totalClients": 141663,
      "totalClientsWithService": 141269,
      "totalClientsWithoutService": 394
    },
    {
      "name": "Caguas",
      "percentageClientsWithService": 99.31,
      "percentageClientsWithoutService": 0.69,
      "totalClients": 250514,
      "totalClientsWithService": 248782,
      "totalClientsWithoutService": 1732
    },
    {
      "name": "Mayaguez",
      "percentageClientsWithService": 99.77,
      "percentageClientsWithoutService": 0.23,
      "totalClients": 216605,
      "totalClientsWithService": 216111,
      "totalClientsWithoutService": 494
    },
    {
      "name": "Ponce",
      "percentageClientsWithService": 97.5,
      "percentageClientsWithoutService": 2.5,
      "totalClients": 212508,
      "totalClientsWithService": 207201,
      "totalClientsWithoutService": 5307
    },
    {
      "name": "San Juan",
      "percentageClientsWithService": 99.65,
      "percentageClientsWithoutService": 0.35,
      "totalClients": 253068,
      "totalClientsWithService": 252189,
      "totalClientsWithoutService": 879
    }
  ],
  "timestamp": "11/17/2023 01:05 PM",
  "timestamp_saved": "11/17/2023 05:05 PM",
  "totals": {
    "totalClients": 1468223,
    "totalClientsWithService": 1458958,
    "totalClientsWithoutService": 9265,
    "totalPercentageWithService": 99.37,
    "totalPercentageWithoutService": 0.63
  }
}