{
  "regions": [
    {
      "name": "Arecibo",
      "percentageClientsWithService": 99.9,
      "percentageClientsWithoutService": 0.1,
      "totalClients": 177369,
      "totalClientsWithService": 177197,
      "totalClientsWithoutService": 172
    },
    {
      "name": "Bayamon",
      "percentageClientsWithService": 100.0,
      "percentageClientsWithoutService": 0.0,
      "totalClients": 216496,
      "totalClientsWithService": 216495,
      "totalClientsWithoutService": 1
    },
    {
      "name": "Carolina",
      "percentageClientsWithService": 100.0,
      "percentageClientsWithoutService": 0.0,
      "totalClients": 141663,
      "totalClientsWithService": 141663,
      "totalClientsWithoutService": 0
    },
    {
      "name": "Caguas",
      "percentageClientsWithService": 99.84,
      "percentageClientsWithoutService": 0.16,
      "totalClients": 250514,
      "totalClientsWithService": 250112,
      "totalClientsWithoutService": 402
    },
    {
      "name": "Mayaguez",
      "percentageClientsWithService": 99.91,
      "percentageClientsWithoutService": 0.09,
      "totalClients": 216605,
      "totalClientsWithService": 216413,
      "totalClientsWithoutService": 192
    },
    {
      "name": "Ponce",
      "percentageClientsWithService": 100.0,
      "percentageClientsWithoutService": 0.0,
      "totalClients": 212508,
      "totalClientsWithService": 212507,
      "totalClientsWithoutService": 1
    },
    {
      "name": "San Juan",
      "percentageClientsWithService": 99.97,
      "percentageClientsWithoutService": 0.03,
      "totalClients": 253068,
      "totalClientsWithService": 253000,
      "totalClientsWithoutService": 68
    }
  ],
  "timestamp": "10/25/2023 03:30 AM",
  "timestamp_saved": "10/25/2023 07:30 AM",
  "totals": {
    "totalClients": 1468223,
    "totalClientsWithService": 1467387,
    "totalClientsWithoutService": 836,
    "totalPercentageWithService": 99.94,
    "totalPercentageWithoutService": 0.06
  }
}