{
  "regions": [
    {
      "name": "Arecibo",
      "percentageClientsWithService": 97.18,
      "percentageClientsWithoutService": 2.82,
      "totalClients": 177369,
      "totalClientsWithService": 172376,
      "totalClientsWithoutService": 4993
    },
    {
      "name": "Bayamon",
      "percentageClientsWithService": 98.66,
      "percentageClientsWithoutService": 1.34,
      "totalClients": 216496,
      "totalClientsWithService": 213590,
      "totalClientsWithoutService": 2906
    },
    {
      "name": "Carolina",
      "percentageClientsWithService": 95.69,
      "percentageClientsWithoutService": 4.31,
      "totalClients": 141663,
      "totalClientsWithService": 135553,
      "totalClientsWithoutService": 6110
    },
    {
      "name": "Caguas",
      "percentageClientsWithService": 99.85,
      "percentageClientsWithoutService": 0.15,
      "totalClients": 250514,
      "totalClientsWithService": 250135,
      "totalClientsWithoutService": 379
    },
    {
      "name": "Mayaguez",
      "percentageClientsWithService": 99.76,
      "percentageClientsWithoutService": 0.24,
      "totalClients": 216605,
      "totalClientsWithService": 216075,
      "totalClientsWithoutService": 530
    },
    {
      "name": "Ponce",
      "percentageClientsWithService": 99.99,
      "percentageClientsWithoutService": 0.01,
      "totalClients": 212508,
      "totalClientsWithService": 212495,
      "totalClientsWithoutService": 13
    },
    {
      "name": "San Juan",
      "percentageClientsWithService": 99.3,
      "percentageClientsWithoutService": 0.7,
      "totalClients": 253068,
      "totalClientsWithService": 251289,
      "totalClientsWithoutService": 1779
    }
  ],
  "timestamp": "08/01/2023 08:55 PM",
  "timestamp_saved": "08/02/2023 12:55 AM",
  "totals": {
    "totalClients": 1468223,
    "totalClientsWithService": 1451513,
    "totalClientsWithoutService": 16710,
    "totalPercentageWithService": 98.86,
    "totalPercentageWithoutService": 1.14
  }
}