{
  "regions": [
    {
      "name": "Arecibo",
      "percentageClientsWithService": 99.79,
      "percentageClientsWithoutService": 0.21,
      "totalClients": 177369,
      "totalClientsWithService": 177001,
      "totalClientsWithoutService": 368
    },
    {
      "name": "Bayamon",
      "percentageClientsWithService": 98.43,
      "percentageClientsWithoutService": 1.57,
      "totalClients": 216496,
      "totalClientsWithService": 213092,
      "totalClientsWithoutService": 3404
    },
    {
      "name": "Carolina",
      "percentageClientsWithService": 99.99,
      "percentageClientsWithoutService": 0.01,
      "totalClients": 141663,
      "totalClientsWithService": 141643,
      "totalClientsWithoutService": 20
    },
    {
      "name": "Caguas",
      "percentageClientsWithService": 99.99,
      "percentageClientsWithoutService": 0.01,
      "totalClients": 250514,
      "totalClientsWithService": 250485,
      "totalClientsWithoutService": 29
    },
    {
      "name": "Mayaguez",
      "percentageClientsWithService": 99.9,
      "percentageClientsWithoutService": 0.1,
      "totalClients": 216605,
      "totalClientsWithService": 216382,
      "totalClientsWithoutService": 223
    },
    {
      "name": "Ponce",
      "percentageClientsWithService": 99.99,
      "percentageClientsWithoutService": 0.01,
      "totalClients": 212508,
      "totalClientsWithService": 212491,
      "totalClientsWithoutService": 17
    },
    {
      "name": "San Juan",
      "percentageClientsWithService": 99.75,
      "percentageClientsWithoutService": 0.25,
      "totalClients": 253068,
      "totalClientsWithService": 252436,
      "totalClientsWithoutService": 632
    }
  ],
  "timestamp": "11/20/2023 07:10 PM",
  "timestamp_saved": "11/20/2023 11:10 PM",
  "totals": {
    "totalClients": 1468223,
    "totalClientsWithService": 1463530,
    "totalClientsWithoutService": 4693,
    "totalPercentageWithService": 99.68,
    "totalPercentageWithoutService": 0.32
  }
}